tests
xcures_api
