Metadata-Version: 2.1
Name: xcures_api
Version: 0.0.3.5
Summary: Python wrapper for the xcures REST api, found here https://partner.xcures.com/api-docs.
Home-page: https://github.com/RCRF/xcures_api
Author: John Major
Author-email: iamh2o@gmail.com
License: MIT
Keywords: xcures api bioinformatics patient records
Classifier: Development Status :: 3 - Alpha
Classifier: Intended Audience :: Developers
Classifier: License :: OSI Approved :: MIT License
Classifier: Programming Language :: Python :: 3.10
Requires-Python: >=3.10
License-File: LICENSE
Requires-Dist: pytest
Requires-Dist: requests
Requires-Dist: yaml_config_day
Requires-Dist: pytz
Requires-Dist: ipython
Requires-Dist: twine
Requires-Dist: black
